Metadata-Version: 1.1
Name: ovh-api-cli
Version: 1.0.4
Summary: A wrapper over OVH's API with killer autocomplete feature.
Home-page: https://api.ovh.com/
Author: Cyril DEMINGEON
Author-email: cyril.demingeon@corp.ovh.com
License: MIT
Keywords: ovh cli api apiv6
Platform: UNKNOWN
Classifier: Topic :: Utilities
Classifier: Environment :: Console
Classifier: Development Status :: 4 - Beta
Classifier: Intended Audience :: Developers
Classifier: License :: OSI Approved :: MIT License
Classifier: Programming Language :: Python :: 2
Classifier: Programming Language :: Python :: 2.6
Classifier: Programming Language :: Python :: 2.7
Classifier: Programming Language :: Python :: 3
Classifier: Programming Language :: Python :: 3.3
Classifier: Programming Language :: Python :: 3.4
Classifier: Programming Language :: Python :: 3.5
